lineindex/__init__.py
lineindex/_version.py
lineindex/cli.py
lineindex/example.py
lineindex/lineindex.py
lineindex-0.1.4.dist-info/METADATA
lineindex-0.1.4.dist-info/WHEEL
lineindex-0.1.4.dist-info/entry_points.txt
lineindex-0.1.4.dist-info/top_level.txt
lineindex-0.1.4.dist-info/RECORD
