Metadata-Version: 2.4
Name: lineindex
Version: 0.1.4
Summary: Fast line-based random access to large text files with optional compression
Author-email: Miroslav Lžičař <mireklzicar@seznam.com>
License: MIT
Classifier: Programming Language :: Python :: 3.8
Classifier: Programming Language :: Python :: 3.9
Classifier: Programming Language :: Python :: 3.10
Classifier: Programming Language :: Python :: 3.11
Classifier: License :: OSI Approved :: MIT License
Classifier: Topic :: Text Processing :: Indexing
Classifier: Topic :: System :: Archiving :: Compression
Classifier: Intended Audience :: Developers
Classifier: Intended Audience :: Science/Research
Requires-Python: >=3.6
Requires-Dist: numpy>=1.20.0
Requires-Dist: tqdm>=4.50.0
Provides-Extra: compression
Requires-Dist: python-idzip>=0.3.3; extra == "compression"
Provides-Extra: lint
Requires-Dist: flake8; extra == "lint"
Requires-Dist: flake8-pyproject; extra == "lint"
Requires-Dist: black; extra == "lint"
Requires-Dist: isort; extra == "lint"
Provides-Extra: test
Requires-Dist: pytest; extra == "test"
Requires-Dist: mypy; extra == "test"
Requires-Dist: pytest-cov; extra == "test"
Provides-Extra: docs
Requires-Dist: sphinx; extra == "docs"
Requires-Dist: sphinx-rtd-theme; extra == "docs"
Requires-Dist: myst-parser; extra == "docs"
Provides-Extra: dev
Requires-Dist: lineindex[compression,docs,lint,test]; extra == "dev"
Requires-Dist: bump2version; extra == "dev"
